LICENSE
ferm_docker/__init__.py
ferm_docker/templates/ferm.j2
ferm_docker-0.1.4.dist-info/entry_points.txt
ferm_docker-0.1.4.dist-info/LICENSE
ferm_docker-0.1.4.dist-info/WHEEL
ferm_docker-0.1.4.dist-info/METADATA
ferm_docker-0.1.4.dist-info/RECORD
