Metadata-Version: 2.1
Name: ferm-docker
Version: 0.1.4
Summary: Automatically generate ferm firewall configuration for a local Docker instance
Home-page: https://github.com/mweinelt/ferm-docker
License: GPL-2.0-only
Keywords: docker,ferm
Author: Martin Weinelt
Requires-Python: >=3.6,<4.0
Classifier: License :: OSI Approved :: GNU General Public License v2 (GPLv2)
Classifier: Programming Language :: Python :: 3
Classifier: Programming Language :: Python :: 3.6
Classifier: Programming Language :: Python :: 3.7
Classifier: Programming Language :: Python :: 3.8
Classifier: Programming Language :: Python :: 3.9
Requires-Dist: Jinja2 (>=2.11.2,<3.0.0)
Requires-Dist: docker (>=4.3.1,<5.0.0)
Project-URL: Repository, https://github.com/mweinelt/ferm-docker
